deepprofile/__init__.py
deepprofile/__main__.py
deepprofile/dcgm.py
deepprofile/nsight.py
deepprofile-0.0.12.dist-info/LICENSE.txt
deepprofile-0.0.12.dist-info/METADATA
deepprofile-0.0.12.dist-info/WHEEL
deepprofile-0.0.12.dist-info/RECORD
