Metadata-Version: 2.1
Name: deepprofile
Version: 0.0.12
Summary: In-code profiling for nVidia gpus
Author: SamKG
Author-email: samyak.k.gupta@gmail.com
Requires-Python: >=3.10,<4.0
Classifier: Programming Language :: Python :: 3
Classifier: Programming Language :: Python :: 3.10
Classifier: Programming Language :: Python :: 3.11
Requires-Dist: cloudpickle (>=2.2.1,<3.0.0)
Requires-Dist: nvtx (>=0.2.5,<0.3.0)
